passcode_link_mailer-0.1.5.dist-info/licenses/LICENSE
simple_mailer/__init__.py
simple_mailer/passcode_link_mailer.py
simple_mailer/templates/minimal_template.html
simple_mailer/templates/modern_template.html
simple_mailer/templates/standard_template.html
passcode_link_mailer-0.1.5.dist-info/METADATA
passcode_link_mailer-0.1.5.dist-info/WHEEL
passcode_link_mailer-0.1.5.dist-info/top_level.txt
passcode_link_mailer-0.1.5.dist-info/RECORD
