Metadata-Version: 2.4
Name: passcode-link-mailer
Version: 0.1.5
Summary: A simple Python library to send email confirmations via Gmail using App Passwords, featuring a unique passcode and a provided link.
Author-email: Jonatan Shaya <jonatan.shaya99@gmail.com>
License-Expression: MIT
Project-URL: Homepage, https://github.com/The-JAR-Team/passcode-link-mailer
Project-URL: Repository, https://github.com/The-JAR-Team/passcode-link-mailer
Project-URL: Bug Tracker, https://github.com/The-JAR-Team/passcode-link-mailer/issues
Keywords: email,gmail,confirmation,passcode,mailer,app password,verification
Classifier: Development Status :: 3 - Alpha
Classifier: Intended Audience :: Developers
Classifier: Operating System :: OS Independent
Classifier: Programming Language :: Python :: 3
Classifier: Programming Language :: Python :: 3.7
Classifier: Programming Language :: Python :: 3.8
Classifier: Programming Language :: Python :: 3.9
Classifier: Programming Language :: Python :: 3.10
Classifier: Programming Language :: Python :: 3.11
Classifier: Programming Language :: Python :: 3.12
Classifier: Topic :: Communications :: Email
Classifier: Topic :: Software Development :: Libraries :: Python Modules
Classifier: Topic :: Utilities
Requires-Python: >=3.7
License-File: LICENSE
Dynamic: license-file
